BPspice-0.1.0.dist-info/METADATA
BPspice-0.1.0.dist-info/WHEEL
BPspice/__init__.py
BPspice/BPspice.cpython-39-darwin.so
BPspice-0.1.0.dist-info/RECORD
